inyourface/Animator.py
inyourface/DefaultCacheProvider.py
inyourface/EffectOrchestrator.py
inyourface/Face.py
inyourface/GStorageCacheProvider.py
inyourface/__init__.py
inyourface/version.py
inyourface/effect/Angry.py
inyourface/effect/Clown.py
inyourface/effect/Crying.py
inyourface/effect/Cryingblood.py
inyourface/effect/Deal.py
inyourface/effect/FlavorEnhance.py
inyourface/effect/Glitter.py
inyourface/effect/Googly.py
inyourface/effect/Gray.py
inyourface/effect/Ham.py
inyourface/effect/Intensifies.py
inyourface/effect/Juggalo.py
inyourface/effect/Lasers.py
inyourface/effect/ShuffleFaces.py
inyourface/effect/Swap.py
inyourface/effect/Thinking.py
inyourface/effect/__init__.py
inyourface/overlays/eye.png
inyourface/overlays/fieri.png
inyourface/overlays/glasses.png
inyourface/overlays/ham.png
inyourface/overlays/juggalo-elements.png
inyourface/overlays/juggalo-mouth.png
inyourface/overlays/mask-elements.png
inyourface/overlays/mask-mouth.png
inyourface/overlays/mask.png
inyourface/overlays/sparkle_1.png
inyourface/overlays/sparkle_2.png
inyourface/overlays/sparkle_3.png
inyourface/overlays/tear.png
inyourface/overlays/tearblood.png
inyourface/overlays/thinking-hand.png
inyourface-0.0.13.data/scripts/inyourface
inyourface-0.0.13.dist-info/LICENSE
inyourface-0.0.13.dist-info/METADATA
inyourface-0.0.13.dist-info/WHEEL
inyourface-0.0.13.dist-info/top_level.txt
inyourface-0.0.13.dist-info/RECORD
