Metadata-Version: 2.1
Name: inyourface
Version: 0.0.13
Summary: In Your Face
Home-page: https://github.com/yacomink/inyourface
Author: Andy Yaco-Mink (@yacomink), Samantha Goldstein (@goldsamantha)
Author-email: inyourface@yacomink.com
License: MIT License
Keywords: dumb gifs juggalos clowns
Platform: UNKNOWN
Requires-Dist: click (==6.7)
Requires-Dist: opencv-python (==3.2.0.6)
Requires-Dist: numpy (==1.12.0)
Requires-Dist: Pillow (==4.1.0)
Requires-Dist: google-cloud-vision (==0.28.0)
Requires-Dist: google-cloud-storage (==1.6.0)
Requires-Dist: sympy
